README.txt
setup.py
collective/__init__.py
collective.fsdsimplifier.egg-info/PKG-INFO
collective.fsdsimplifier.egg-info/SOURCES.txt
collective.fsdsimplifier.egg-info/dependency_links.txt
collective.fsdsimplifier.egg-info/entry_points.txt
collective.fsdsimplifier.egg-info/namespace_packages.txt
collective.fsdsimplifier.egg-info/not-zip-safe
collective.fsdsimplifier.egg-info/requires.txt
collective.fsdsimplifier.egg-info/top_level.txt
collective/fsdsimplifier/__init__.py
collective/fsdsimplifier/configure.zcml
collective/fsdsimplifier/permissions.zcml
collective/fsdsimplifier/person.py
collective/fsdsimplifier/profiles.zcml
collective/fsdsimplifier/setuphandlers.py
collective/fsdsimplifier/tests.py
collective/fsdsimplifier/utility.py
collective/fsdsimplifier/version.txt
collective/fsdsimplifier/Extensions/Install.py
collective/fsdsimplifier/browser/__init__.py
collective/fsdsimplifier/browser/configure.zcml
collective/fsdsimplifier/browser/interfaces.py
collective/fsdsimplifier/browser/utils.py
collective/fsdsimplifier/browser/viewlets.py
collective/fsdsimplifier/profiles/default/actions.xml
collective/fsdsimplifier/profiles/default/browserlayer.xml
collective/fsdsimplifier/profiles/default/collective.fsdsimplifier_various.txt
collective/fsdsimplifier/profiles/default/metadata.xml
collective/fsdsimplifier/profiles/default/types.xml
collective/fsdsimplifier/profiles/default/workflows.xml
collective/fsdsimplifier/profiles/default/types/FSDPerson.xml
collective/fsdsimplifier/profiles/default/workflows/fsd_simplifier_person_workflow/definition.xml
collective/fsdsimplifier/profiles/uninstall/actions.xml
collective/fsdsimplifier/profiles/uninstall/collective.fsdsimplifier_removevarious.txt
collective/fsdsimplifier/profiles/uninstall/metadata.xml
collective/fsdsimplifier/profiles/uninstall/workflows.xml
docs/HISTORY.txt
docs/INSTALL.txt
docs/LICENSE.GPL
docs/LICENSE.txt