Metadata-Version: 1.0
Name: collective.fsdsimplifier
Version: 1.3
Summary: Simplifies FacultyStaffDirectory (FSD) for the end-user.
Home-page: http://svn.plone.org/svn/collective/
Author: Heather Wozniak
Author-email: heather@laplone.org
License: GPL
Keywords: web zope plone facultystaffdirectory
Platform: UNKNOWN
Classifier: Framework :: Plone
Classifier: Programming Language :: Python
Classifier: Topic :: Software Development :: Libraries :: Python Modules
